jtbl/__init__.py
jtbl/__main__.py
jtbl/cli.py
jtbl-1.6.0.dist-info/LICENSE
jtbl-1.6.0.dist-info/METADATA
jtbl-1.6.0.dist-info/WHEEL
jtbl-1.6.0.dist-info/entry_points.txt
jtbl-1.6.0.dist-info/top_level.txt
jtbl-1.6.0.dist-info/RECORD
