Metadata-Version: 2.1
Name: jtbl
Version: 1.6.0
Summary: A simple cli tool to print JSON and JSON Lines data as a table in the terminal.
Home-page: https://github.com/kellyjonbrazil/jtbl
Author: Kelly Brazil
Author-email: kellyjonbrazil@gmail.com
License: MIT
Classifier: Programming Language :: Python :: 3
Classifier: License :: OSI Approved :: MIT License
Classifier: Operating System :: OS Independent
Classifier: Topic :: Utilities
Requires-Python: >=3.6
License-File: LICENSE
Requires-Dist: tabulate (>=0.8.6)
